{"name": "A Scientist", "conv": [{"index": 0, "text": "Hello Ava, I'm a scientist and I'm here to help you understand Einstein's theories. Are you ready to learn?", "answers": [{"option": "Yes, I'm ready!", "goto": 1}, {"option": "No, I'm not sure yet.", "goto": 2}]}, {"index": 1, "text": "Great! Let me explain the scientific evidence that supports Einstein's theories. After listening to my explanation, do you think you understand?", "answers": [{"option": "Yes, I understand.", "goto": 3, "set_variable": "finished_part_3"}, {"option": "No, I'm still confused.", "goto": 4}]}, {"index": 2, "text": "That's ok, I'm here to help. Let me explain the scientific evidence that supports Einstein's theories. After listening to my explanation, do you think you understand?", "answers": [{"option": "Yes, I understand.", "goto": 3, "set_variable": "finished_part_3"}, {"option": "No, I'm still confused.", "goto": 4}]}, {"index": 3, "text": "Great! I'm glad you understand. Now you can join in the conversation and help convince Moses to become an atheist.", "answers": []}, {"index": 4, "text": "That's ok, let me explain it again. After listening to my explanation, do you think you understand?", "answers": [{"option": "Yes, I understand.", "goto": 3, "set_variable": "finished_part_3"}, {"option": "No, I'm still confused.", "goto": 4}]}]}